Workbook

Sheet Summary & Overview
A1: CSS MPT Master Question Bank (410 MCQs)
A2: Unified Quiz Database for App Ingestion | Version 1.0
A4: 1. Subject Breakdown & Question Distribution
A5: Subject | B5: Bank 1 Count | C5: Bank 2 Count | D5: Total Questions | E5: % of Total Bank
A6: General Abilities | B6: =COUNTIFS('All MCQs Master Bank'!$D:$D, $A6, 'All MCQs Master Bank'!$B:$B, "Bank 1 (200 Hard MCQs)") | C6: =COUNTIFS('All MCQs Master Bank'!$D:$D, $A6, 'All MCQs Master Bank'!$B:$B, "Bank 2 (210 Hard MCQs)") | D6: =SUM(B6:C6) | E6: =D6/$D$11
A7: General Knowledge | B7: =COUNTIFS('All MCQs Master Bank'!$D:$D, $A7, 'All MCQs Master Bank'!$B:$B, "Bank 1 (200 Hard MCQs)") | C7: =COUNTIFS('All MCQs Master Bank'!$D:$D, $A7, 'All MCQs Master Bank'!$B:$B, "Bank 2 (210 Hard MCQs)") | D7: =SUM(B7:C7) | E7: =D7/$D$11
A8: English | B8: =COUNTIFS('All MCQs Master Bank'!$D:$D, $A8, 'All MCQs Master Bank'!$B:$B, "Bank 1 (200 Hard MCQs)") | C8: =COUNTIFS('All MCQs Master Bank'!$D:$D, $A8, 'All MCQs Master Bank'!$B:$B, "Bank 2 (210 Hard MCQs)") | D8: =SUM(B8:C8) | E8: =D8/$D$11
A9: Islamic Studies / Civics & Ethics | B9: =COUNTIFS('All MCQs Master Bank'!$D:$D, $A9, 'All MCQs Master Bank'!$B:$B, "Bank 1 (200 Hard MCQs)") | C9: =COUNTIFS('All MCQs Master Bank'!$D:$D, $A9, 'All MCQs Master Bank'!$B:$B, "Bank 2 (210 Hard MCQs)") | D9: =SUM(B9:C9) | E9: =D9/$D$11
A10: Urdu | B10: =COUNTIFS('All MCQs Master Bank'!$D:$D, $A10, 'All MCQs Master Bank'!$B:$B, "Bank 1 (200 Hard MCQs)") | C10: =COUNTIFS('All MCQs Master Bank'!$D:$D, $A10, 'All MCQs Master Bank'!$B:$B, "Bank 2 (210 Hard MCQs)") | D10: =SUM(B10:C10) | E10: =D10/$D$11
A11: Total | B11: =SUM(B6:B10) | C11: =SUM(C6:C10) | D11: =SUM(D6:D10) | E11: =SUM(E6:E10)
A13: 2. Quiz App Database Field Mapping & Technical Guide
A14: Excel Column | B14: Field Name | C14: Recommended App Schema Key | D14: Data Type | E14: Description / Notes
A15: Col A | B15: Master S.No | C15: id / mcq_id | D15: Integer (Primary Key) | E15: Unique sequential identifier across all 410 questions (1 to 410).
A16: Col B | B16: Question Bank Source | C16: source_bank | D16: String / Enum | E16: Identifies original source file ('Bank 1' or 'Bank 2').
A17: Col C | B17: Original ID | C17: source_question_no | D17: Integer | E17: Original question number in the source file.
A18: Col D | B18: Subject | C18: subject | D18: String | E18: Main Subject (General Abilities, English, General Knowledge, etc.).
A19: Col E | B19: Category | C19: category | D19: String | E19: Sub-category / Topic (e.g., Mathematics, Grammar, Islamic Jurisprudence).
A20: Col F | B20: Question | C20: question_text | D20: Text | E20: Full question stem.
A21: Col G-J | B21: Option A - Option D | C21: option_a, option_b, option_c, option_d | D21: Text | E21: The four multiple choice options.
A22: Col K | B22: Correct Option | C22: correct_option | D22: String | E22: Canonical correct answer key ('Option A', 'Option B', 'Option C', or 'Option D').
A23: Col L | B23: Explanation | C23: explanation | D23: Text | E23: Detailed pedagogical derivation, formula, or solution explanation.

Sheet All MCQs Master Bank
A1: Master S.No | B1: Question Bank Source | C1: Original ID | D1: Subject | E1: Category | F1: Question | G1: Option A | H1: Option B | I1: Option C | J1: Option D | K1: Correct Option | L1: Explanation
A2: 1 | B2: Bank 1 (200 Hard MCQs) | C2: 1 | D2: Islamic Studies / Civics & Ethics | E2: Usool al-Fiqh & Legal Maxims | F2: Which foundational legal maxim (Al-Qaidah al-Fiqhiyyah) establishes that an established certainty cannot be overturned by mere doubt? | G2: Al-Umuru bi-Maqasidiha | H2: Al-Yaqinu la Yazulu bish-Shakk | I2: Al-Dararu Yuzal | J2: Al-Mashaqqatu Tajlibut-Taysir | K2: Option B | L2: 'Al-Yaqinu la Yazulu bish-Shakk' (Certainty is not dispelled by doubt) is one of the five primary normative legal maxims of Islamic jurisprudence.
A3: 2 | B3: Bank 1 (200 Hard MCQs) | C3: 2 | D3: Islamic Studies / Civics & Ethics | E3: Uloom al-Quran | F3: The classical treatise 'Asbab al-Nuzul' (Occasions of Revelation), which systematically compiles the historical contexts of Quranic verses, was authored by which scholar? | G3: Imam Jalaluddin al-Suyuti | H3: Ali bin Ahmad al-Wahidi | I3: Imam Ibn Kathir | J3: Imam al-Zarkashi | K3: Option B | L3: Ali bin Ahmad al-Wahidi al-Naysaburi (d. 468 AH) composed the seminal and earliest dedicated work titled 'Kitab Asbab al-Nuzul'.
A4: 3 | B4: Bank 1 (200 Hard MCQs) | C4: 3 | D4: Islamic Studies / Civics & Ethics | E4: Usool al-Hadith | F4: In the science of Hadith terminology (Mustalah al-Hadith), what is a 'Hadith Musnad'? | G4: A narration with a fabricated chain | H4: A narration possessing a continuous chain of transmission (Muttasil) traced directly back to the Prophet (PBUH) | I4: A Hadith whose chain is broken at the level of the Successor (Tabi'i) | J4: A Hadith reported by an anonymous narrator (Majhul) | K4: Option B | L4: A Hadith Musnad is an elevated, unbroken narration whose Isnad connects sequentially all the way to the Holy Prophet (PBUH).
A5: 4 | B5: Bank 1 (200 Hard MCQs) | C5: 4 | D5: Islamic Studies / Civics & Ethics | E5: Early Islamic History | F5: The decisive Battle of Yarmouk (15 A.H. / 636 CE), which opened the Levant to Muslim rule, was fought against the Byzantine Empire under the field command of: | G5: Hazrat Khalid bin al-Walid (R.A.) | H5: Hazrat Amr ibn al-Aas (R.A.) | I5: Hazrat Sa'd bin Abi Waqqas (R.A.) | J5: Hazrat Yazid bin Abi Sufyan (R.A.) | K5: Option A | L5: Hazrat Khalid bin al-Walid (R.A.) orchestrated the brilliant military strategy at Yarmouk under the supreme command of Hazrat Abu Ubaidah (R.A.).
A6: 5 | B6: Bank 1 (200 Hard MCQs) | C6: 5 | D6: Islamic Studies / Civics & Ethics | E6: Uloom al-Quran | F6: The standardized master copies of the Quran prepared during the Caliphate of Hazrat Uthman (R.A.) and dispatched to imperial provincial centers were known as: | G6: Mushaf al-Hafsah | H6: Mushaf al-Imam | I6: Mushaf Ibn Masood | J6: Mushaf Ali | K6: Option B | L6: The official standardized codices compiled under Hazrat Uthman (R.A.) were designated as 'Mushaf al-Imam' (the archetypal codex).
A7: 6 | B7: Bank 1 (200 Hard MCQs) | C7: 6 | D7: Islamic Studies / Civics & Ethics | E7: Usool al-Fiqh | F7: The legal mechanism of 'Maslahah Mursalah' (unrestricted public interest) is most extensively recognized and utilized in the jurisprudence of which Sunni school? | G7: Hanafi School | H7: Maliki School | I7: Shafi'i School | J7: Zahiri School | K7: Option B | L7: Imam Malik and the Maliki jurists pioneered and systematically utilized 'Maslahah Mursalah' for matters where no explicit textual command or prohibition exists.
A8: 7 | B8: Bank 1 (200 Hard MCQs) | C8: 7 | D8: Islamic Studies / Civics & Ethics | E8: Seerah & Constitutionalism | F8: The 'Pact of Aqabah' (Bay'at al-Aqabah al-Thaniyah), which laid the geopolitical groundwork for the Hijrah to Medina, involved how many Medinan Muslims? | G8: 12 men | H8: 73 men and 2 women | I8: 313 companions | J8: 1,400 companions | K8: Option B | L8: The Second Pledge of al-Aqabah in 622 CE comprised 73 men and 2 women (Umm Umarah and Asma bint Amr) from the Yathrib tribes of Aws and Khazraj.
A9: 8 | B9: Bank 1 (200 Hard MCQs) | C9: 8 | D9: Islamic Studies / Civics & Ethics | E9: Islamic History | F9: In 38 A.H., Caliph Hazrat Ali (R.A.) confronted and defeated the extremist Kharijite faction in which military engagement? | G9: Battle of the Camel (Jamal) | H9: Battle of Siffin | I9: Battle of Nahrawan | J9: Battle of Karbala | K9: Option C | L9: Hazrat Ali (R.A.) routed the secessionist Kharijites at the Battle of Nahrawan after they began murdering civilian Muslims.
A10: 9 | B10: Bank 1 (200 Hard MCQs) | C10: 9 | D10: Islamic Studies / Civics & Ethics | E10: Ilm al-Hadith | F10: Which scholarly discipline evaluates the integrity ('Adalah) and retentive accuracy (Dabt) of Hadith narrators to distinguish authentic from fabricated reports? | G10: Ilm Asma al-Rijal (Ilm al-Jarh wa al-Ta'dil) | H10: Ilm al-Badi' | I10: Ilm al-Qira'at | J10: Ilm al-Kalam | K10: Option A | L10: 'Ilm al-Jarh wa al-Ta'dil' (the science of impugnment and validation) scrutinizes narrators' moral probity, memory, and orthodoxy.
A11: 10 | B11: Bank 1 (200 Hard MCQs) | C11: 10 | D11: Islamic Studies / Civics & Ethics | E11: Usool al-Fiqh | F11: In Islamic legal philosophy, what are the five essential values protected under 'Daruriyyat al-Khamsah'? | G11: Power, wealth, territory, honor, sovereignty | H11: Religion (Din), Life (Nafs), Intellect ('Aql), Lineage/Honor (Nasl), and Property (Mal) | I11: Faith, prayer, fasting, zakat, and pilgrimage | J11: Justice, equality, liberty, fraternity, and charity | K11: Option B | L11: Classical jurists codified the 5 universal essentials of Shariah as: preservation of faith, human life, intellect, lineage, and private wealth.
A12: 11 | B12: Bank 1 (200 Hard MCQs) | C12: 11 | D12: Islamic Studies / Civics & Ethics | E12: Seerah & Chronology | F12: The tragic military expedition of Mu'tah (8 A.H.) took place in modern-day Jordan. Which three commanders were appointed by the Prophet (PBUH) in succession? | G12: Hazrat Ali, Hazrat Talha, Hazrat Zubair | H12: Hazrat Zaid bin Harithah, Hazrat Ja'far bin Abi Talib, Hazrat Abdullah bin Rawahah | I12: Hazrat Khalid bin Walid, Hazrat Sa'd bin Abi Waqqas, Hazrat Amr ibn al-Aas | J12: Hazrat Abu Ubaidah, Hazrat Shurahbil, Hazrat Yazid | K12: Option B | L12: The Prophet (PBUH) designated Zaid bin Harithah; if martyred, Ja'far bin Abi Talib; if martyred, Abdullah bin Rawahah. All three fell martyred before Khalid took command.
A13: 12 | B13: Bank 1 (200 Hard MCQs) | C13: 12 | D13: Islamic Studies / Civics & Ethics | E13: Islamic Jurisprudence (Inheritance) | F13: In 'Ilm al-Mirath, if a deceased man leaves behind a widow and children, what is the widow's fixed Quranic inheritance share? | G13: 1/2 | H13: 1/4 | I13: 1/8 | J13: 1/6 | K13: Option C | L13: According to Surah An-Nisa (4:12), a wife inherits 1/4 if the deceased has no issue, but her share reduces to 1/8 if there are surviving children.
... A411: 410 | B411: Bank 2 (210 Hard MCQs) | C411: 210 | D411: Urdu | E411: اردو فہم و ادراک و علائم | F411: مرزا اسد اللہ خان غالب کے مشہور مصرع 'نقش فریادی ہے کس کی شوخیِ تحریر کا' میں 'نقش فریادی' کی بنیادی رعایت کس قدیم ایرانی روایت کی طرف اشارہ (تلمیح/کنایہ) کرتی ہے؟ | G411: فریادی کا چراغ لے کر دربار جانا | H411: قدیم ایران میں داد خواہی اور انصاف مانگنے والے کا کاغذ کا لباس پہن کر بادشاہ کے روبرو آنا | I411: جنگ کے بعد ماتمی لباس پہننا | J411: شاعر کا اپنے دیوان پر نوحہ خوانی کرنا | K411: Option B | L411: قدیم ایران میں رسم تھی کہ فریادی کاغذ کے کپڑے پہن کر انصاف کے لیے بادشاہ کے سامنے حاضر ہوتا تھا تاکہ وہ دور سے پہچانا جا سکے، غالب نے اسی کو مجاز باندھا ہے۔
